envcat.py
envcat-0.1.1.dist-info/DESCRIPTION.rst
envcat-0.1.1.dist-info/METADATA
envcat-0.1.1.dist-info/RECORD
envcat-0.1.1.dist-info/WHEEL
envcat-0.1.1.dist-info/entry_points.txt
envcat-0.1.1.dist-info/metadata.json
envcat-0.1.1.dist-info/top_level.txt
