Metadata-Version: 2.0
Name: envcat
Version: 0.1.1
Summary: Mix and merge env file values
Home-page: https://github.com/pmac/envcat
Author: Paul McLanahan
Author-email: pmac@mozilla.com
License: Apache Software License 2.0
Keywords: envcat
Platform: UNKNOWN
Classifier: Development Status :: 2 - Pre-Alpha
Classifier: Intended Audience :: Developers
Classifier: License :: OSI Approved :: Apache Software License
Classifier: Natural Language :: English
Classifier: Programming Language :: Python :: 2
Classifier: Programming Language :: Python :: 2.6
Classifier: Programming Language :: Python :: 2.7
Classifier: Programming Language :: Python :: 3
Classifier: Programming Language :: Python :: 3.3
Classifier: Programming Language :: Python :: 3.4
Classifier: Programming Language :: Python :: 3.5
